dingtalk_client_rick/__init__.py
dingtalk_client_rick/base.py
dingtalk_client_rick/bot.py
dingtalk_client_rick/table.py
dingtalk_client_rick/uploadfile.py
dingtalk_client_rick/user.py
dingtalk_client_rick-0.1.0.dist-info/METADATA
dingtalk_client_rick-0.1.0.dist-info/WHEEL
dingtalk_client_rick-0.1.0.dist-info/entry_points.txt
dingtalk_client_rick-0.1.0.dist-info/RECORD
