Metadata-Version: 2.4
Name: dingtalk-client-rick
Version: 0.1.0
Summary: Add your description here
Author-email: LH <276069869@qq.com>
Requires-Python: >=3.13
Requires-Dist: cachetools>=6.2.4
Requires-Dist: jsonpath-ng>=1.7.0
Requires-Dist: python-dotenv>=1.2.1
Requires-Dist: requests>=2.32.5
Requires-Dist: tqdm>=4.67.1
